{
  "updated": 1656374275.021,
  "current_price": 1193.78,
  "data": {
    "OpenSea": {
      "total_tco2": 852306.5346815921,
      "daily_tco2": 282.89595903669084
    },
    "Nifty Gateway": {
      "total_tco2": 49672.86644406908,
      "daily_tco2": 14.925526074000768
    },
    "Rarible": {
      "total_tco2": 26029.31968855491,
      "daily_tco2": 9.829844883510045
    },
    "Foundation": {
      "total_tco2": 22587.854966705665,
      "daily_tco2": 82.41012409755162
    },
    "Makersplace": {
      "total_tco2": 3195.3610396287986,
      "daily_tco2": 1.281257348401206
    },
    "SuperRare": {
      "total_tco2": 3430.9650843682466,
      "daily_tco2": 1.7908162389482771
    }
  }
}
